MANIFEST.in
README.rst
setup.cfg
setup.py
Products/__init__.py
Products.FaqAttachment.egg-info/PKG-INFO
Products.FaqAttachment.egg-info/SOURCES.txt
Products.FaqAttachment.egg-info/dependency_links.txt
Products.FaqAttachment.egg-info/entry_points.txt
Products.FaqAttachment.egg-info/namespace_packages.txt
Products.FaqAttachment.egg-info/not-zip-safe
Products.FaqAttachment.egg-info/requires.txt
Products.FaqAttachment.egg-info/top_level.txt
Products/FaqAttachment/__init__.py
Products/FaqAttachment/configure.zcml
Products/FaqAttachment/interfaces.py
Products/FaqAttachment/schema_extender.py
Products/FaqAttachment/Extensions/install.py
Products/FaqAttachment/browser/__init__.py
Products/FaqAttachment/browser/configure.zcml
Products/FaqAttachment/browser/faqentry_view.pt
Products/FaqAttachment/browser/faqfolder_view.pt
Products/FaqAttachment/locales/Products.FaqAttachment-manual.pot
Products/FaqAttachment/locales/Products.FaqAttachment.pot
Products/FaqAttachment/locales/rebuilPo.sh
Products/FaqAttachment/locales/it/LC_MESSAGES/Products.FaqAttachment.mo
Products/FaqAttachment/locales/it/LC_MESSAGES/Products.FaqAttachment.po
Products/FaqAttachment/profiles/default/browserlayer.xml
Products/FaqAttachment/profiles/default/metadata.xml
Products/FaqAttachment/profiles/uninstall/browserlayer.xml
docs/HISTORY.txt
docs/INSTALL.txt
docs/LICENSE.GPL
docs/LICENSE.txt