Metadata-Version: 1.1
Name: Products.FaqAttachment
Version: 0.1
Summary: Attachment support for Products.Faq
Home-page: http://plone.org/products/faqattachment
Author: RedTurtle Technology
Author-email: sviluppoplone@redturtle.it
License: GPL
Keywords: plone plonegov faq
Platform: UNKNOWN
Classifier: Framework :: Plone
Classifier: Framework :: Plone :: 3.3
Classifier: Programming Language :: Python
